{"kind":"symbol","schemaVersion":{"patch":0,"major":0,"minor":3},"identifier":{"url":"doc:\/\/ATProtoKit\/documentation\/ATProtoKit\/ATProtoKit\/createRecord(repositoryDID:collection:recordKey:shouldValidate:record:swapCommit:)","interfaceLanguage":"swift"},"sections":[],"primaryContentSections":[{"kind":"declarations","declarations":[{"tokens":[{"kind":"keyword","text":"func"},{"text":" ","kind":"text"},{"kind":"identifier","text":"createRecord"},{"text":"(","kind":"text"},{"text":"repositoryDID","kind":"externalParam"},{"kind":"text","text":": "},{"text":"String","preciseIdentifier":"s:SS","kind":"typeIdentifier"},{"text":", ","kind":"text"},{"text":"collection","kind":"externalParam"},{"kind":"text","text":": "},{"text":"String","kind":"typeIdentifier","preciseIdentifier":"s:SS"},{"kind":"text","text":", "},{"kind":"externalParam","text":"recordKey"},{"text":": ","kind":"text"},{"preciseIdentifier":"s:SS","text":"String","kind":"typeIdentifier"},{"text":"? = nil, ","kind":"text"},{"text":"shouldValidate","kind":"externalParam"},{"text":": ","kind":"text"},{"kind":"typeIdentifier","text":"Bool","preciseIdentifier":"s:Sb"},{"text":"? = true, ","kind":"text"},{"text":"record","kind":"externalParam"},{"kind":"text","text":": "},{"identifier":"doc:\/\/ATProtoKit\/documentation\/ATProtoKit\/UnknownType","kind":"typeIdentifier","text":"UnknownType","preciseIdentifier":"s:10ATProtoKit11UnknownTypeO"},{"kind":"text","text":", "},{"text":"swapCommit","kind":"externalParam"},{"kind":"text","text":": "},{"preciseIdentifier":"s:SS","text":"String","kind":"typeIdentifier"},{"text":"? = nil) ","kind":"text"},{"text":"async","kind":"keyword"},{"text":" ","kind":"text"},{"text":"throws","kind":"keyword"},{"text":" -> ","kind":"text"},{"text":"ComAtprotoLexicon","identifier":"doc:\/\/ATProtoKit\/documentation\/ATProtoKit\/ComAtprotoLexicon","kind":"typeIdentifier","preciseIdentifier":"s:10ATProtoKit17ComAtprotoLexiconV"},{"text":".","kind":"text"},{"text":"Repository","identifier":"doc:\/\/ATProtoKit\/documentation\/ATProtoKit\/ComAtprotoLexicon\/Repository","preciseIdentifier":"s:10ATProtoKit17ComAtprotoLexiconV10RepositoryV","kind":"typeIdentifier"},{"text":".","kind":"text"},{"identifier":"doc:\/\/ATProtoKit\/documentation\/ATProtoKit\/ComAtprotoLexicon\/Repository\/StrongReference","text":"StrongReference","kind":"typeIdentifier","preciseIdentifier":"s:10ATProtoKit17ComAtprotoLexiconV10RepositoryV15StrongReferenceV"}],"platforms":["macOS"],"languages":["swift"]}]},{"parameters":[{"content":[{"inlineContent":[{"type":"text","text":"The decentralized identifier (DID) of the repository."}],"type":"paragraph"}],"name":"repositoryDID"},{"content":[{"inlineContent":[{"type":"text","text":"The Namespaced Identifier (NSID) of the record."}],"type":"paragraph"}],"name":"collection"},{"content":[{"type":"paragraph","inlineContent":[{"type":"text","text":"The record key of the collection. Optional."}]}],"name":"recordKey"},{"name":"shouldValidate","content":[{"type":"paragraph","inlineContent":[{"text":"ndicates whether the record should be validated. Optional. Defaults to ","type":"text"},{"type":"codeVoice","code":"true"},{"text":".","type":"text"}]}]},{"name":"record","content":[{"type":"paragraph","inlineContent":[{"type":"text","text":"The record itself."}]}]},{"name":"swapCommit","content":[{"inlineContent":[{"type":"text","text":"Swaps out an operation based on the CID. Optional."}],"type":"paragraph"}]}],"kind":"parameters"},{"kind":"content","content":[{"anchor":"return-value","level":2,"type":"heading","text":"Return Value"},{"type":"paragraph","inlineContent":[{"type":"text","text":"A"},{"type":"text","text":" "},{"type":"reference","identifier":"doc:\/\/ATProtoKit\/documentation\/ATProtoKit\/ComAtprotoLexicon\/Repository\/StrongReference","isActive":true},{"type":"text","text":" "},{"type":"text","text":"structure which represents the record that was successfully created."}]}]},{"kind":"content","content":[{"anchor":"discussion","type":"heading","level":2,"text":"Discussion"},{"style":"warning","name":"Warning","type":"aside","content":[{"inlineContent":[{"type":"text","text":"If you’re using a lexicon that’s not made by "},{"code":"com.atproto","type":"codeVoice"},{"text":" or ","type":"text"},{"code":"app.bsky","type":"codeVoice"},{"text":",","type":"text"},{"type":"text","text":" "},{"text":"make sure you set ","type":"text"},{"code":"shouldValidate","type":"codeVoice"},{"type":"text","text":" to "},{"code":"false","type":"codeVoice"},{"text":". Failure to do so will result in an error","type":"text"},{"type":"text","text":" "},{"type":"text","text":"that the lexicon isn’t found."}],"type":"paragraph"}]},{"style":"note","type":"aside","content":[{"inlineContent":[{"type":"text","text":"According to the AT Protocol specifications: “Create a single new repository"},{"type":"text","text":" "},{"text":"record. Requires auth, implemented by PDS.”","type":"text"}],"type":"paragraph"}],"name":"Note"},{"type":"aside","content":[{"inlineContent":[{"text":"This is based on the ","type":"text"},{"identifier":"https:\/\/github.com\/bluesky-social\/atproto\/blob\/main\/lexicons\/com\/atproto\/repo\/createRecord.json","isActive":true,"type":"reference"},{"text":" lexicon.","type":"text"}],"type":"paragraph"}],"name":"See Also","style":"note"},{"content":[{"inlineContent":[{"type":"text","text":"An "},{"type":"reference","identifier":"doc:\/\/ATProtoKit\/documentation\/ATProtoKit\/ATProtoError","isActive":true},{"type":"text","text":"-conforming error type, depending on the issue. Go to"},{"text":" ","type":"text"},{"type":"reference","identifier":"doc:\/\/ATProtoKit\/documentation\/ATProtoKit\/ATAPIError","isActive":true},{"text":" and ","type":"text"},{"identifier":"doc:\/\/ATProtoKit\/documentation\/ATProtoKit\/ATRequestPrepareError","isActive":true,"type":"reference"},{"text":" for more details.","type":"text"}],"type":"paragraph"}],"style":"note","type":"aside","name":"Throws"}]}],"abstract":[{"type":"text","text":"Creates a record attached to a user account."}],"metadata":{"title":"createRecord(repositoryDID:collection:recordKey:shouldValidate:record:swapCommit:)","modules":[{"name":"ATProtoKit"}],"remoteSource":{"fileName":"CreateRecord.swift","url":"https:\/\/github.com\/MasterJ93\/ATProtoKit\/tree\/main\/Sources\/ATProtoKit\/APIReference\/ComAtprotoAPI\/CreateRecord.swift#L38"},"externalID":"s:10ATProtoKitAAC12createRecord13repositoryDID10collection9recordKey14shouldValidate0H010swapCommitAA17ComAtprotoLexiconV10RepositoryV15StrongReferenceVSS_S2SSgSbSgAA11UnknownTypeOAPtYaKF","role":"symbol","symbolKind":"method","extendedModule":"ATProtoKit","fragments":[{"kind":"keyword","text":"func"},{"text":" ","kind":"text"},{"kind":"identifier","text":"createRecord"},{"text":"(","kind":"text"},{"kind":"externalParam","text":"repositoryDID"},{"kind":"text","text":": "},{"text":"String","preciseIdentifier":"s:SS","kind":"typeIdentifier"},{"kind":"text","text":", "},{"kind":"externalParam","text":"collection"},{"text":": ","kind":"text"},{"kind":"typeIdentifier","preciseIdentifier":"s:SS","text":"String"},{"text":", ","kind":"text"},{"text":"recordKey","kind":"externalParam"},{"text":": ","kind":"text"},{"text":"String","kind":"typeIdentifier","preciseIdentifier":"s:SS"},{"kind":"text","text":"?, "},{"text":"shouldValidate","kind":"externalParam"},{"text":": ","kind":"text"},{"kind":"typeIdentifier","text":"Bool","preciseIdentifier":"s:Sb"},{"text":"?, ","kind":"text"},{"text":"record","kind":"externalParam"},{"kind":"text","text":": "},{"preciseIdentifier":"s:10ATProtoKit11UnknownTypeO","text":"UnknownType","kind":"typeIdentifier"},{"text":", ","kind":"text"},{"text":"swapCommit","kind":"externalParam"},{"text":": ","kind":"text"},{"preciseIdentifier":"s:SS","text":"String","kind":"typeIdentifier"},{"text":"?) ","kind":"text"},{"text":"async","kind":"keyword"},{"kind":"text","text":" "},{"kind":"keyword","text":"throws"},{"text":" -> ","kind":"text"},{"preciseIdentifier":"s:10ATProtoKit17ComAtprotoLexiconV","text":"ComAtprotoLexicon","kind":"typeIdentifier"},{"text":".","kind":"text"},{"preciseIdentifier":"s:10ATProtoKit17ComAtprotoLexiconV10RepositoryV","kind":"typeIdentifier","text":"Repository"},{"kind":"text","text":"."},{"text":"StrongReference","preciseIdentifier":"s:10ATProtoKit17ComAtprotoLexiconV10RepositoryV15StrongReferenceV","kind":"typeIdentifier"}],"roleHeading":"Instance Method"},"variants":[{"traits":[{"interfaceLanguage":"swift"}],"paths":["\/documentation\/atprotokit\/atprotokit\/createrecord(repositorydid:collection:recordkey:shouldvalidate:record:swapcommit:)"]}],"hierarchy":{"paths":[["doc:\/\/ATProtoKit\/documentation\/ATProtoKit","doc:\/\/ATProtoKit\/documentation\/ATProtoKit\/ATProtoKit"]]},"references":{"doc://ATProtoKit/documentation/ATProtoKit/ComAtprotoLexicon/Repository/StrongReference":{"url":"\/documentation\/atprotokit\/comatprotolexicon\/repository\/strongreference","role":"symbol","abstract":[{"type":"text","text":"A main data model definition for a strong reference."}],"navigatorTitle":[{"kind":"identifier","text":"StrongReference"}],"kind":"symbol","identifier":"doc:\/\/ATProtoKit\/documentation\/ATProtoKit\/ComAtprotoLexicon\/Repository\/StrongReference","title":"ComAtprotoLexicon.Repository.StrongReference","type":"topic","fragments":[{"kind":"keyword","text":"struct"},{"text":" ","kind":"text"},{"text":"StrongReference","kind":"identifier"}]},"doc://ATProtoKit/documentation/ATProtoKit/ATRequestPrepareError":{"type":"topic","abstract":[{"type":"text","text":"An error type related to issues surrounding preparing a request to be sent."}],"fragments":[{"kind":"keyword","text":"enum"},{"kind":"text","text":" "},{"kind":"identifier","text":"ATRequestPrepareError"}],"kind":"symbol","title":"ATRequestPrepareError","url":"\/documentation\/atprotokit\/atrequestprepareerror","navigatorTitle":[{"text":"ATRequestPrepareError","kind":"identifier"}],"identifier":"doc:\/\/ATProtoKit\/documentation\/ATProtoKit\/ATRequestPrepareError","role":"symbol"},"atprotokit_icon.png":{"alt":"A technology icon representing the ATProtoKit framework.","type":"image","identifier":"atprotokit_icon.png","variants":[{"traits":["1x","light"],"url":"\/images\/atprotokit_icon.png"}]},"doc://ATProtoKit/documentation/ATProtoKit/ComAtprotoLexicon":{"url":"\/documentation\/atprotokit\/comatprotolexicon","role":"symbol","abstract":[{"type":"text","text":"A group of lexicons within the "},{"code":"com.atproto","type":"codeVoice"},{"type":"text","text":" namespace."}],"navigatorTitle":[{"text":"ComAtprotoLexicon","kind":"identifier"}],"kind":"symbol","identifier":"doc:\/\/ATProtoKit\/documentation\/ATProtoKit\/ComAtprotoLexicon","title":"ComAtprotoLexicon","type":"topic","fragments":[{"kind":"keyword","text":"struct"},{"text":" ","kind":"text"},{"text":"ComAtprotoLexicon","kind":"identifier"}]},"doc://ATProtoKit/documentation/ATProtoKit/ATProtoError":{"abstract":[{"type":"text","text":"The base exception class for ATProtoKit."}],"navigatorTitle":[{"kind":"identifier","text":"ATProtoError"}],"identifier":"doc:\/\/ATProtoKit\/documentation\/ATProtoKit\/ATProtoError","title":"ATProtoError","fragments":[{"text":"protocol","kind":"keyword"},{"kind":"text","text":" "},{"kind":"identifier","text":"ATProtoError"}],"type":"topic","url":"\/documentation\/atprotokit\/atprotoerror","role":"symbol","kind":"symbol"},"doc://ATProtoKit/documentation/ATProtoKit/ATAPIError":{"type":"topic","abstract":[{"text":"The base exception class for ATProtoKit’s API requests.","type":"text"}],"fragments":[{"kind":"keyword","text":"enum"},{"kind":"text","text":" "},{"kind":"identifier","text":"ATAPIError"}],"kind":"symbol","title":"ATAPIError","url":"\/documentation\/atprotokit\/atapierror","navigatorTitle":[{"kind":"identifier","text":"ATAPIError"}],"identifier":"doc:\/\/ATProtoKit\/documentation\/ATProtoKit\/ATAPIError","role":"symbol"},"https://github.com/bluesky-social/atproto/blob/main/lexicons/com/atproto/repo/createRecord.json":{"type":"link","identifier":"https:\/\/github.com\/bluesky-social\/atproto\/blob\/main\/lexicons\/com\/atproto\/repo\/createRecord.json","titleInlineContent":[{"type":"codeVoice","code":"com.atproto.repo.createRecord"}],"title":"com.atproto.repo.createRecord","url":"https:\/\/github.com\/bluesky-social\/atproto\/blob\/main\/lexicons\/com\/atproto\/repo\/createRecord.json"},"doc://ATProtoKit/documentation/ATProtoKit/ATProtoKit/createRecord(repositoryDID:collection:recordKey:shouldValidate:record:swapCommit:)":{"fragments":[{"text":"func","kind":"keyword"},{"kind":"text","text":" "},{"kind":"identifier","text":"createRecord"},{"text":"(","kind":"text"},{"kind":"externalParam","text":"repositoryDID"},{"text":": ","kind":"text"},{"preciseIdentifier":"s:SS","kind":"typeIdentifier","text":"String"},{"text":", ","kind":"text"},{"kind":"externalParam","text":"collection"},{"text":": ","kind":"text"},{"kind":"typeIdentifier","preciseIdentifier":"s:SS","text":"String"},{"text":", ","kind":"text"},{"text":"recordKey","kind":"externalParam"},{"kind":"text","text":": "},{"kind":"typeIdentifier","preciseIdentifier":"s:SS","text":"String"},{"kind":"text","text":"?, "},{"kind":"externalParam","text":"shouldValidate"},{"kind":"text","text":": "},{"text":"Bool","kind":"typeIdentifier","preciseIdentifier":"s:Sb"},{"kind":"text","text":"?, "},{"text":"record","kind":"externalParam"},{"text":": ","kind":"text"},{"preciseIdentifier":"s:10ATProtoKit11UnknownTypeO","text":"UnknownType","kind":"typeIdentifier"},{"kind":"text","text":", "},{"text":"swapCommit","kind":"externalParam"},{"text":": ","kind":"text"},{"preciseIdentifier":"s:SS","text":"String","kind":"typeIdentifier"},{"kind":"text","text":"?) "},{"text":"async","kind":"keyword"},{"kind":"text","text":" "},{"text":"throws","kind":"keyword"},{"text":" -> ","kind":"text"},{"kind":"typeIdentifier","text":"ComAtprotoLexicon","preciseIdentifier":"s:10ATProtoKit17ComAtprotoLexiconV"},{"text":".","kind":"text"},{"text":"Repository","preciseIdentifier":"s:10ATProtoKit17ComAtprotoLexiconV10RepositoryV","kind":"typeIdentifier"},{"text":".","kind":"text"},{"preciseIdentifier":"s:10ATProtoKit17ComAtprotoLexiconV10RepositoryV15StrongReferenceV","text":"StrongReference","kind":"typeIdentifier"}],"title":"createRecord(repositoryDID:collection:recordKey:shouldValidate:record:swapCommit:)","url":"\/documentation\/atprotokit\/atprotokit\/createrecord(repositorydid:collection:recordkey:shouldvalidate:record:swapcommit:)","type":"topic","role":"symbol","kind":"symbol","abstract":[{"type":"text","text":"Creates a record attached to a user account."}],"identifier":"doc:\/\/ATProtoKit\/documentation\/ATProtoKit\/ATProtoKit\/createRecord(repositoryDID:collection:recordKey:shouldValidate:record:swapCommit:)"},"doc://ATProtoKit/documentation/ATProtoKit/ATProtoKit":{"type":"topic","abstract":[{"type":"text","text":"The base class that handles the main functionality of the "},{"code":"ATProtoKit","type":"codeVoice"},{"text":" API library.","type":"text"}],"fragments":[{"kind":"keyword","text":"class"},{"kind":"text","text":" "},{"kind":"identifier","text":"ATProtoKit"}],"kind":"symbol","title":"ATProtoKit","url":"\/documentation\/atprotokit\/atprotokit","navigatorTitle":[{"kind":"identifier","text":"ATProtoKit"}],"identifier":"doc:\/\/ATProtoKit\/documentation\/ATProtoKit\/ATProtoKit","role":"symbol"},"doc://ATProtoKit/documentation/ATProtoKit":{"type":"topic","identifier":"doc:\/\/ATProtoKit\/documentation\/ATProtoKit","abstract":[{"text":"Develop and manage client and server-side applications for the AT Protocol and Bluesky.","type":"text"}],"role":"collection","title":"ATProtoKit","kind":"symbol","url":"\/documentation\/atprotokit","images":[{"type":"icon","identifier":"atprotokit_icon.png"}]},"doc://ATProtoKit/documentation/ATProtoKit/ComAtprotoLexicon/Repository":{"url":"\/documentation\/atprotokit\/comatprotolexicon\/repository","role":"symbol","abstract":[{"type":"text","text":"A group of lexicons within the "},{"code":"com.atproto.repo","type":"codeVoice"},{"type":"text","text":" namespace."}],"navigatorTitle":[{"text":"Repository","kind":"identifier"}],"kind":"symbol","title":"ComAtprotoLexicon.Repository","identifier":"doc:\/\/ATProtoKit\/documentation\/ATProtoKit\/ComAtprotoLexicon\/Repository","type":"topic","fragments":[{"text":"struct","kind":"keyword"},{"kind":"text","text":" "},{"kind":"identifier","text":"Repository"}]},"doc://ATProtoKit/documentation/ATProtoKit/UnknownType":{"role":"symbol","url":"\/documentation\/atprotokit\/unknowntype","type":"topic","abstract":[{"type":"text","text":"Handles decoding and encoding of records when their type is not known ahead of type."}],"kind":"symbol","identifier":"doc:\/\/ATProtoKit\/documentation\/ATProtoKit\/UnknownType","navigatorTitle":[{"text":"UnknownType","kind":"identifier"}],"title":"UnknownType","fragments":[{"text":"enum","kind":"keyword"},{"text":" ","kind":"text"},{"kind":"identifier","text":"UnknownType"}]}}}