{"identifier":{"interfaceLanguage":"swift","url":"doc:\/\/ATProtoKit\/documentation\/ATProtoKit\/ATProtoAdmin\/updateCommunicationTemplate(_:name:language:contentMarkdown:subject:updatedBy:isDisabled:)"},"schemaVersion":{"minor":3,"patch":0,"major":0},"hierarchy":{"paths":[["doc:\/\/ATProtoKit\/documentation\/ATProtoKit","doc:\/\/ATProtoKit\/documentation\/ATProtoKit\/ATProtoAdmin"]]},"sections":[],"abstract":[{"type":"text","text":"Updates a communication template."}],"primaryContentSections":[{"declarations":[{"tokens":[{"text":"func","kind":"keyword"},{"text":" ","kind":"text"},{"kind":"identifier","text":"updateCommunicationTemplate"},{"text":"(","kind":"text"},{"kind":"externalParam","text":"_"},{"text":" ","kind":"text"},{"text":"id","kind":"internalParam"},{"kind":"text","text":": "},{"preciseIdentifier":"s:SS","text":"String","kind":"typeIdentifier"},{"kind":"text","text":", "},{"text":"name","kind":"externalParam"},{"text":": ","kind":"text"},{"kind":"typeIdentifier","text":"String","preciseIdentifier":"s:SS"},{"text":"? = nil, ","kind":"text"},{"kind":"externalParam","text":"language"},{"kind":"text","text":": "},{"kind":"typeIdentifier","text":"Locale","preciseIdentifier":"s:10Foundation6LocaleV"},{"kind":"text","text":"?, "},{"kind":"externalParam","text":"contentMarkdown"},{"text":": ","kind":"text"},{"preciseIdentifier":"s:SS","kind":"typeIdentifier","text":"String"},{"kind":"text","text":"? = nil, "},{"text":"subject","kind":"externalParam"},{"kind":"text","text":": "},{"preciseIdentifier":"s:SS","text":"String","kind":"typeIdentifier"},{"text":"? = nil, ","kind":"text"},{"kind":"externalParam","text":"updatedBy"},{"text":": ","kind":"text"},{"text":"String","kind":"typeIdentifier","preciseIdentifier":"s:SS"},{"kind":"text","text":"? = nil, "},{"text":"isDisabled","kind":"externalParam"},{"text":": ","kind":"text"},{"text":"Bool","kind":"typeIdentifier","preciseIdentifier":"s:Sb"},{"kind":"text","text":"? = nil) "},{"kind":"keyword","text":"async"},{"text":" ","kind":"text"},{"text":"throws","kind":"keyword"},{"kind":"text","text":" -> "},{"identifier":"doc:\/\/ATProtoKit\/documentation\/ATProtoKit\/ToolsOzoneLexicon","preciseIdentifier":"s:10ATProtoKit17ToolsOzoneLexiconV","kind":"typeIdentifier","text":"ToolsOzoneLexicon"},{"text":".","kind":"text"},{"preciseIdentifier":"s:10ATProtoKit17ToolsOzoneLexiconV13CommunicationV","identifier":"doc:\/\/ATProtoKit\/documentation\/ATProtoKit\/ToolsOzoneLexicon\/Communication","kind":"typeIdentifier","text":"Communication"},{"kind":"text","text":"."},{"identifier":"doc:\/\/ATProtoKit\/documentation\/ATProtoKit\/ToolsOzoneLexicon\/Communication\/TemplateViewDefinition","text":"TemplateViewDefinition","kind":"typeIdentifier","preciseIdentifier":"s:10ATProtoKit17ToolsOzoneLexiconV13CommunicationV22TemplateViewDefinitionV"}],"platforms":["macOS"],"languages":["swift"]}],"kind":"declarations"},{"parameters":[{"content":[{"type":"paragraph","inlineContent":[{"type":"text","text":"The ID of the communication template."}]}],"name":"id"},{"name":"name","content":[{"type":"paragraph","inlineContent":[{"text":"The name of the communication template. Optional.","type":"text"}]}]},{"name":"language","content":[{"type":"paragraph","inlineContent":[{"type":"text","text":"The language of the message. Optional."}]}]},{"name":"contentMarkdown","content":[{"inlineContent":[{"text":"The content of the communication template. Optional.","type":"text"}],"type":"paragraph"}]},{"content":[{"type":"paragraph","inlineContent":[{"type":"text","text":"The subject line of the message itself. Optional."}]}],"name":"subject"},{"content":[{"type":"paragraph","inlineContent":[{"text":"The decentralized identifier (DID) of the user who updated the","type":"text"},{"text":" ","type":"text"},{"type":"text","text":"communication template. Optional."}]}],"name":"updatedBy"},{"content":[{"type":"paragraph","inlineContent":[{"text":"Indicates whether the communication template is disabled. Optional.","type":"text"}]}],"name":"isDisabled"}],"kind":"parameters"},{"content":[{"anchor":"return-value","text":"Return Value","type":"heading","level":2},{"inlineContent":[{"type":"text","text":"The recently-updated communication template."}],"type":"paragraph"}],"kind":"content"},{"kind":"content","content":[{"text":"Discussion","type":"heading","anchor":"discussion","level":2},{"type":"aside","name":"Important","style":"important","content":[{"inlineContent":[{"type":"text","text":"This is a moderator task and as such, regular users won’t be able to access"},{"type":"text","text":" "},{"text":"this; if they attempt to do so, an error will occur.","type":"text"}],"type":"paragraph"}]},{"style":"note","name":"Note","content":[{"type":"paragraph","inlineContent":[{"type":"text","text":"According to the AT Protocol specifications: “Administrative action to update an"},{"type":"text","text":" "},{"type":"text","text":"existing communication template. Allows passing partial fields to patch specific fields only.”"}]}],"type":"aside"},{"type":"aside","content":[{"type":"paragraph","inlineContent":[{"text":"This is based on the ","type":"text"},{"identifier":"https:\/\/github.com\/bluesky-social\/atproto\/blob\/main\/lexicons\/tools\/ozone\/communication\/updateTemplate.json","type":"reference","isActive":true},{"text":" lexicon.","type":"text"}]}],"name":"See Also","style":"note"},{"name":"Throws","style":"note","content":[{"inlineContent":[{"type":"text","text":"An "},{"isActive":true,"identifier":"doc:\/\/ATProtoKit\/documentation\/ATProtoKit\/ATProtoError","type":"reference"},{"type":"text","text":"-conforming error type, depending on the issue. Go to"},{"text":" ","type":"text"},{"isActive":true,"type":"reference","identifier":"doc:\/\/ATProtoKit\/documentation\/ATProtoKit\/ATAPIError"},{"type":"text","text":" and "},{"identifier":"doc:\/\/ATProtoKit\/documentation\/ATProtoKit\/ATRequestPrepareError","isActive":true,"type":"reference"},{"type":"text","text":" for more details."}],"type":"paragraph"}],"type":"aside"}]}],"variants":[{"paths":["\/documentation\/atprotokit\/atprotoadmin\/updatecommunicationtemplate(_:name:language:contentmarkdown:subject:updatedby:isdisabled:)"],"traits":[{"interfaceLanguage":"swift"}]}],"kind":"symbol","metadata":{"extendedModule":"ATProtoKit","externalID":"s:10ATProtoKit0A5AdminC27updateCommunicationTemplate_4name8language15contentMarkdown7subject9updatedBy10isDisabledAA17ToolsOzoneLexiconV0E0V0F14ViewDefinitionVSS_SSSg10Foundation6LocaleVSgA3QSbSgtYaKF","modules":[{"name":"ATProtoKit"}],"roleHeading":"Instance Method","remoteSource":{"fileName":"UpdateCommunicationTemplateAsAdmin.swift","url":"https:\/\/github.com\/MasterJ93\/ATProtoKit\/tree\/main\/Sources\/ATProtoKit\/APIReference\/AdminAndModeratorAPI\/UpdateCommunicationTemplateAsAdmin.swift#L37"},"title":"updateCommunicationTemplate(_:name:language:contentMarkdown:subject:updatedBy:isDisabled:)","role":"symbol","symbolKind":"method","fragments":[{"text":"func","kind":"keyword"},{"text":" ","kind":"text"},{"kind":"identifier","text":"updateCommunicationTemplate"},{"text":"(","kind":"text"},{"text":"String","preciseIdentifier":"s:SS","kind":"typeIdentifier"},{"text":", ","kind":"text"},{"text":"name","kind":"externalParam"},{"text":": ","kind":"text"},{"text":"String","kind":"typeIdentifier","preciseIdentifier":"s:SS"},{"text":"?, ","kind":"text"},{"kind":"externalParam","text":"language"},{"text":": ","kind":"text"},{"preciseIdentifier":"s:10Foundation6LocaleV","text":"Locale","kind":"typeIdentifier"},{"text":"?, ","kind":"text"},{"text":"contentMarkdown","kind":"externalParam"},{"text":": ","kind":"text"},{"text":"String","kind":"typeIdentifier","preciseIdentifier":"s:SS"},{"text":"?, ","kind":"text"},{"text":"subject","kind":"externalParam"},{"text":": ","kind":"text"},{"kind":"typeIdentifier","text":"String","preciseIdentifier":"s:SS"},{"kind":"text","text":"?, "},{"kind":"externalParam","text":"updatedBy"},{"text":": ","kind":"text"},{"preciseIdentifier":"s:SS","kind":"typeIdentifier","text":"String"},{"kind":"text","text":"?, "},{"text":"isDisabled","kind":"externalParam"},{"kind":"text","text":": "},{"text":"Bool","kind":"typeIdentifier","preciseIdentifier":"s:Sb"},{"kind":"text","text":"?) "},{"text":"async","kind":"keyword"},{"text":" ","kind":"text"},{"kind":"keyword","text":"throws"},{"kind":"text","text":" -> "},{"kind":"typeIdentifier","preciseIdentifier":"s:10ATProtoKit17ToolsOzoneLexiconV","text":"ToolsOzoneLexicon"},{"kind":"text","text":"."},{"preciseIdentifier":"s:10ATProtoKit17ToolsOzoneLexiconV13CommunicationV","text":"Communication","kind":"typeIdentifier"},{"kind":"text","text":"."},{"text":"TemplateViewDefinition","preciseIdentifier":"s:10ATProtoKit17ToolsOzoneLexiconV13CommunicationV22TemplateViewDefinitionV","kind":"typeIdentifier"}]},"references":{"atprotokit_icon.png":{"type":"image","alt":"A technology icon representing the ATProtoKit framework.","identifier":"atprotokit_icon.png","variants":[{"url":"\/images\/atprotokit_icon.png","traits":["1x","light"]}]},"https://github.com/bluesky-social/atproto/blob/main/lexicons/tools/ozone/communication/updateTemplate.json":{"url":"https:\/\/github.com\/bluesky-social\/atproto\/blob\/main\/lexicons\/tools\/ozone\/communication\/updateTemplate.json","type":"link","identifier":"https:\/\/github.com\/bluesky-social\/atproto\/blob\/main\/lexicons\/tools\/ozone\/communication\/updateTemplate.json","titleInlineContent":[{"code":"tools.ozone.communication.updateTemplate","type":"codeVoice"}],"title":"tools.ozone.communication.updateTemplate"},"doc://ATProtoKit/documentation/ATProtoKit/ATProtoAdmin":{"navigatorTitle":[{"text":"ATProtoAdmin","kind":"identifier"}],"abstract":[{"type":"text","text":"A class containing all administrator and moderator functionality of the "},{"code":"ATProtoKit","type":"codeVoice"},{"type":"text","text":" "},{"type":"text","text":"API library."}],"title":"ATProtoAdmin","fragments":[{"text":"class","kind":"keyword"},{"kind":"text","text":" "},{"text":"ATProtoAdmin","kind":"identifier"}],"kind":"symbol","type":"topic","url":"\/documentation\/atprotokit\/atprotoadmin","role":"symbol","identifier":"doc:\/\/ATProtoKit\/documentation\/ATProtoKit\/ATProtoAdmin"},"doc://ATProtoKit/documentation/ATProtoKit":{"identifier":"doc:\/\/ATProtoKit\/documentation\/ATProtoKit","title":"ATProtoKit","abstract":[{"type":"text","text":"Develop and manage client and server-side applications for the AT Protocol and Bluesky."}],"images":[{"type":"icon","identifier":"atprotokit_icon.png"}],"kind":"symbol","role":"collection","type":"topic","url":"\/documentation\/atprotokit"},"doc://ATProtoKit/documentation/ATProtoKit/ToolsOzoneLexicon":{"role":"symbol","kind":"symbol","navigatorTitle":[{"text":"ToolsOzoneLexicon","kind":"identifier"}],"fragments":[{"text":"struct","kind":"keyword"},{"kind":"text","text":" "},{"text":"ToolsOzoneLexicon","kind":"identifier"}],"abstract":[{"type":"text","text":"A group of lexicons within the "},{"code":"tools.ozone","type":"codeVoice"},{"type":"text","text":" namespace."}],"title":"ToolsOzoneLexicon","identifier":"doc:\/\/ATProtoKit\/documentation\/ATProtoKit\/ToolsOzoneLexicon","url":"\/documentation\/atprotokit\/toolsozonelexicon","type":"topic"},"doc://ATProtoKit/documentation/ATProtoKit/ATProtoError":{"fragments":[{"kind":"keyword","text":"protocol"},{"kind":"text","text":" "},{"kind":"identifier","text":"ATProtoError"}],"navigatorTitle":[{"text":"ATProtoError","kind":"identifier"}],"title":"ATProtoError","url":"\/documentation\/atprotokit\/atprotoerror","kind":"symbol","type":"topic","identifier":"doc:\/\/ATProtoKit\/documentation\/ATProtoKit\/ATProtoError","role":"symbol","abstract":[{"text":"The base exception class for ATProtoKit.","type":"text"}]},"doc://ATProtoKit/documentation/ATProtoKit/ToolsOzoneLexicon/Communication/TemplateViewDefinition":{"title":"ToolsOzoneLexicon.Communication.TemplateViewDefinition","identifier":"doc:\/\/ATProtoKit\/documentation\/ATProtoKit\/ToolsOzoneLexicon\/Communication\/TemplateViewDefinition","type":"topic","role":"symbol","abstract":[{"type":"text","text":"A definition model for a communication template."}],"fragments":[{"text":"struct","kind":"keyword"},{"text":" ","kind":"text"},{"text":"TemplateViewDefinition","kind":"identifier"}],"kind":"symbol","navigatorTitle":[{"kind":"identifier","text":"TemplateViewDefinition"}],"url":"\/documentation\/atprotokit\/toolsozonelexicon\/communication\/templateviewdefinition"},"doc://ATProtoKit/documentation/ATProtoKit/ATProtoAdmin/updateCommunicationTemplate(_:name:language:contentMarkdown:subject:updatedBy:isDisabled:)":{"abstract":[{"type":"text","text":"Updates a communication template."}],"role":"symbol","url":"\/documentation\/atprotokit\/atprotoadmin\/updatecommunicationtemplate(_:name:language:contentmarkdown:subject:updatedby:isdisabled:)","kind":"symbol","identifier":"doc:\/\/ATProtoKit\/documentation\/ATProtoKit\/ATProtoAdmin\/updateCommunicationTemplate(_:name:language:contentMarkdown:subject:updatedBy:isDisabled:)","title":"updateCommunicationTemplate(_:name:language:contentMarkdown:subject:updatedBy:isDisabled:)","fragments":[{"text":"func","kind":"keyword"},{"text":" ","kind":"text"},{"kind":"identifier","text":"updateCommunicationTemplate"},{"kind":"text","text":"("},{"kind":"typeIdentifier","text":"String","preciseIdentifier":"s:SS"},{"text":", ","kind":"text"},{"kind":"externalParam","text":"name"},{"text":": ","kind":"text"},{"text":"String","kind":"typeIdentifier","preciseIdentifier":"s:SS"},{"text":"?, ","kind":"text"},{"text":"language","kind":"externalParam"},{"text":": ","kind":"text"},{"text":"Locale","preciseIdentifier":"s:10Foundation6LocaleV","kind":"typeIdentifier"},{"text":"?, ","kind":"text"},{"text":"contentMarkdown","kind":"externalParam"},{"text":": ","kind":"text"},{"kind":"typeIdentifier","text":"String","preciseIdentifier":"s:SS"},{"kind":"text","text":"?, "},{"kind":"externalParam","text":"subject"},{"text":": ","kind":"text"},{"text":"String","preciseIdentifier":"s:SS","kind":"typeIdentifier"},{"kind":"text","text":"?, "},{"text":"updatedBy","kind":"externalParam"},{"text":": ","kind":"text"},{"text":"String","preciseIdentifier":"s:SS","kind":"typeIdentifier"},{"kind":"text","text":"?, "},{"kind":"externalParam","text":"isDisabled"},{"kind":"text","text":": "},{"text":"Bool","kind":"typeIdentifier","preciseIdentifier":"s:Sb"},{"kind":"text","text":"?) "},{"text":"async","kind":"keyword"},{"kind":"text","text":" "},{"text":"throws","kind":"keyword"},{"text":" -> ","kind":"text"},{"text":"ToolsOzoneLexicon","kind":"typeIdentifier","preciseIdentifier":"s:10ATProtoKit17ToolsOzoneLexiconV"},{"kind":"text","text":"."},{"text":"Communication","kind":"typeIdentifier","preciseIdentifier":"s:10ATProtoKit17ToolsOzoneLexiconV13CommunicationV"},{"text":".","kind":"text"},{"text":"TemplateViewDefinition","kind":"typeIdentifier","preciseIdentifier":"s:10ATProtoKit17ToolsOzoneLexiconV13CommunicationV22TemplateViewDefinitionV"}],"type":"topic"},"doc://ATProtoKit/documentation/ATProtoKit/ToolsOzoneLexicon/Communication":{"role":"symbol","abstract":[{"text":"A group of lexicons within the ","type":"text"},{"code":"tools.ozone.communication","type":"codeVoice"},{"type":"text","text":" namespace."}],"title":"ToolsOzoneLexicon.Communication","type":"topic","kind":"symbol","identifier":"doc:\/\/ATProtoKit\/documentation\/ATProtoKit\/ToolsOzoneLexicon\/Communication","fragments":[{"text":"struct","kind":"keyword"},{"text":" ","kind":"text"},{"text":"Communication","kind":"identifier"}],"navigatorTitle":[{"text":"Communication","kind":"identifier"}],"url":"\/documentation\/atprotokit\/toolsozonelexicon\/communication"},"doc://ATProtoKit/documentation/ATProtoKit/ATRequestPrepareError":{"role":"symbol","url":"\/documentation\/atprotokit\/atrequestprepareerror","kind":"symbol","abstract":[{"type":"text","text":"An error type related to issues surrounding preparing a request to be sent."}],"navigatorTitle":[{"kind":"identifier","text":"ATRequestPrepareError"}],"title":"ATRequestPrepareError","fragments":[{"text":"enum","kind":"keyword"},{"text":" ","kind":"text"},{"text":"ATRequestPrepareError","kind":"identifier"}],"identifier":"doc:\/\/ATProtoKit\/documentation\/ATProtoKit\/ATRequestPrepareError","type":"topic"},"doc://ATProtoKit/documentation/ATProtoKit/ATAPIError":{"title":"ATAPIError","url":"\/documentation\/atprotokit\/atapierror","role":"symbol","abstract":[{"type":"text","text":"The base exception class for ATProtoKit’s API requests."}],"identifier":"doc:\/\/ATProtoKit\/documentation\/ATProtoKit\/ATAPIError","navigatorTitle":[{"kind":"identifier","text":"ATAPIError"}],"type":"topic","kind":"symbol","fragments":[{"text":"enum","kind":"keyword"},{"text":" ","kind":"text"},{"kind":"identifier","text":"ATAPIError"}]}}}